MANIFEST.in
README.rst
setup.py
google/__init__.py
google/streetview/__init__.py
google/streetview/publish/__init__.py
google/streetview/publish/v1/__init__.py
google/streetview/publish/v1/enums.py
google/streetview/publish/v1/street_view_publish_service_client.py
google/streetview/publish/v1/street_view_publish_service_client_config.json
google_maps_streetview_publish_v1.egg-info/PKG-INFO
google_maps_streetview_publish_v1.egg-info/SOURCES.txt
google_maps_streetview_publish_v1.egg-info/dependency_links.txt
google_maps_streetview_publish_v1.egg-info/namespace_packages.txt
google_maps_streetview_publish_v1.egg-info/requires.txt
google_maps_streetview_publish_v1.egg-info/top_level.txt